Workbook

Sheet Orders
A1: Order ID | B1: Order Date | C1: Region | D1: Country | E1: Product ID | F1: Product | G1: Category | H1: Units | I1: Unit Price (EUR) | J1: Discount % | K1: Revenue (EUR) | L1: Cost (EUR) | M1: Gross Margin (EUR) | N1: Channel | O1: Sales Rep
A2: SO-25001 | B2: 45658 | C2: Western Europe | D2: Spain | E2: P-110 | F2: =INDEX(Products!$B$2:$B$9,MATCH(E2,Products!$A$2:$A$9,0)) -> Sensor Hub Pro | G2: =INDEX(Products!$C$2:$C$9,MATCH(E2,Products!$A$2:$A$9,0)) -> Hardware | H2: 1 | I2: =INDEX(Products!$D$2:$D$9,MATCH(E2,Products!$A$2:$A$9,0)) -> 349 | J2: 0.15 | K2: =H2*I2*(1-J2) -> 296.65 | L2: =H2*INDEX(Products!$E$2:$E$9,MATCH(E2,Products!$A$2:$A$9,0)) -> 201 | M2: =K2-L2 -> 95.65 | N2: Partner | O2: Marc Dubois
A3: SO-25002 | B3: 45658 | C3: Western Europe | D3: France | E3: P-100 | F3: =INDEX(Products!$B$2:$B$9,MATCH(E3,Products!$A$2:$A$9,0)) -> Sensor Hub S | G3: =INDEX(Products!$C$2:$C$9,MATCH(E3,Products!$A$2:$A$9,0)) -> Hardware | H3: 2 | I3: =INDEX(Products!$D$2:$D$9,MATCH(E3,Products!$A$2:$A$9,0)) -> 189 | J3: 0.1 | K3: =H3*I3*(1-J3) -> 340.2 | L3: =H3*INDEX(Products!$E$2:$E$9,MATCH(E3,Products!$A$2:$A$9,0)) -> 196 | M3: =K3-L3 -> 144.2 | N3: Partner | O3: Marc Dubois
A4: SO-25003 | B4: 45658 | C4: Western Europe | D4: Italy | E4: P-200 | F4: =INDEX(Products!$B$2:$B$9,MATCH(E4,Products!$A$2:$A$9,0)) -> Analytics Basic | G4: =INDEX(Products!$C$2:$C$9,MATCH(E4,Products!$A$2:$A$9,0)) -> Software | H4: 1 | I4: =INDEX(Products!$D$2:$D$9,MATCH(E4,Products!$A$2:$A$9,0)) -> 120 | J4: 0.1 | K4: =H4*I4*(1-J4) -> 108 | L4: =H4*INDEX(Products!$E$2:$E$9,MATCH(E4,Products!$A$2:$A$9,0)) -> 18 | M4: =K4-L4 -> 90 | N4: Partner | O4: Marc Dubois
A5: SO-25004 | B5: 45659 | C5: Western Europe | D5: Spain | E5: P-110 | F5: =INDEX(Products!$B$2:$B$9,MATCH(E5,Products!$A$2:$A$9,0)) -> Sensor Hub Pro | G5: =INDEX(Products!$C$2:$C$9,MATCH(E5,Products!$A$2:$A$9,0)) -> Hardware | H5: 4 | I5: =INDEX(Products!$D$2:$D$9,MATCH(E5,Products!$A$2:$A$9,0)) -> 349 | J5: 0.05 | K5: =H5*I5*(1-J5) -> 1326.2 | L5: =H5*INDEX(Products!$E$2:$E$9,MATCH(E5,Products!$A$2:$A$9,0)) -> 804 | M5: =K5-L5 -> 522.2 | N5: Direct | O5: Marc Dubois
A6: SO-25005 | B6: 45659 | C6: Asia Pacific | D6: Japan | E6: P-210 | F6: =INDEX(Products!$B$2:$B$9,MATCH(E6,Products!$A$2:$A$9,0)) -> Analytics Plus | G6: =INDEX(Products!$C$2:$C$9,MATCH(E6,Products!$A$2:$A$9,0)) -> Software | H6: 1 | I6: =INDEX(Products!$D$2:$D$9,MATCH(E6,Products!$A$2:$A$9,0)) -> 290 | J6: 0.15 | K6: =H6*I6*(1-J6) -> 246.5 | L6: =H6*INDEX(Products!$E$2:$E$9,MATCH(E6,Products!$A$2:$A$9,0)) -> 41 | M6: =K6-L6 -> 205.5 | N6: Partner | O6: Priya Nair
A7: SO-25006 | B7: 45659 | C7: Western Europe | D7: Portugal | E7: P-110 | F7: =INDEX(Products!$B$2:$B$9,MATCH(E7,Products!$A$2:$A$9,0)) -> Sensor Hub Pro | G7: =INDEX(Products!$C$2:$C$9,MATCH(E7,Products!$A$2:$A$9,0)) -> Hardware | H7: 20 | I7: =INDEX(Products!$D$2:$D$9,MATCH(E7,Products!$A$2:$A$9,0)) -> 349 | J7: 0.25 | K7: =H7*I7*(1-J7) -> 5235 | L7: =H7*INDEX(Products!$E$2:$E$9,MATCH(E7,Products!$A$2:$A$9,0)) -> 4020 | M7: =K7-L7 -> 1215 | N7: Partner | O7: Lucia Romero
A8: SO-25007 | B8: 45660 | C8: Western Europe | D8: Spain | E8: P-110 | F8: =INDEX(Products!$B$2:$B$9,MATCH(E8,Products!$A$2:$A$9,0)) -> Sensor Hub Pro | G8: =INDEX(Products!$C$2:$C$9,MATCH(E8,Products!$A$2:$A$9,0)) -> Hardware | H8: 1 | I8: =INDEX(Products!$D$2:$D$9,MATCH(E8,Products!$A$2:$A$9,0)) -> 349 | J8: 0.15 | K8: =H8*I8*(1-J8) -> 296.65 | L8: =H8*INDEX(Products!$E$2:$E$9,MATCH(E8,Products!$A$2:$A$9,0)) -> 201 | M8: =K8-L8 -> 95.65 | N8: Online | O8: Marc Dubois
A9: SO-25008 | B9: 45660 | C9: Western Europe | D9: France | E9: P-210 | F9: =INDEX(Products!$B$2:$B$9,MATCH(E9,Products!$A$2:$A$9,0)) -> Analytics Plus | G9: =INDEX(Products!$C$2:$C$9,MATCH(E9,Products!$A$2:$A$9,0)) -> Software | H9: 1 | I9: =INDEX(Products!$D$2:$D$9,MATCH(E9,Products!$A$2:$A$9,0)) -> 290 | J9: 0 | K9: =H9*I9*(1-J9) -> 290 | L9: =H9*INDEX(Products!$E$2:$E$9,MATCH(E9,Products!$A$2:$A$9,0)) -> 41 | M9: =K9-L9 -> 249 | N9: Direct | O9: Marc Dubois
A10: SO-25009 | B10: 45660 | C10: North America | D10: United States | E10: P-210 | F10: =INDEX(Products!$B$2:$B$9,MATCH(E10,Products!$A$2:$A$9,0)) -> Analytics Plus | G10: =INDEX(Products!$C$2:$C$9,MATCH(E10,Products!$A$2:$A$9,0)) -> Software | H10: 1 | I10: =INDEX(Products!$D$2:$D$9,MATCH(E10,Products!$A$2:$A$9,0)) -> 290 | J10: 0.1 | K10: =H10*I10*(1-J10) -> 261 | L10: =H10*INDEX(Products!$E$2:$E$9,MATCH(E10,Products!$A$2:$A$9,0)) -> 41 | M10: =K10-L10 -> 220 | N10: Partner | O10: Emily Carter
A11: SO-25010 | B11: 45663 | C11: Western Europe | D11: Portugal | E11: P-110 | F11: =INDEX(Products!$B$2:$B$9,MATCH(E11,Products!$A$2:$A$9,0)) -> Sensor Hub Pro | G11: =INDEX(Products!$C$2:$C$9,MATCH(E11,Products!$A$2:$A$9,0)) -> Hardware | H11: 1 | I11: =INDEX(Products!$D$2:$D$9,MATCH(E11,Products!$A$2:$A$9,0)) -> 349 | J11: 0 | K11: =H11*I11*(1-J11) -> 349 | L11: =H11*INDEX(Products!$E$2:$E$9,MATCH(E11,Products!$A$2:$A$9,0)) -> 201 | M11: =K11-L11 -> 148 | N11: Direct | O11: Marc Dubois
A12: SO-25011 | B12: 45663 | C12: Western Europe | D12: France | E12: P-110 | F12: =INDEX(Products!$B$2:$B$9,MATCH(E12,Products!$A$2:$A$9,0)) -> Sensor Hub Pro | G12: =INDEX(Products!$C$2:$C$9,MATCH(E12,Products!$A$2:$A$9,0)) -> Hardware | H12: 12 | I12: =INDEX(Products!$D$2:$D$9,MATCH(E12,Products!$A$2:$A$9,0)) -> 349 | J12: 0 | K12: =H12*I12*(1-J12) -> 4188 | L12: =H12*INDEX(Products!$E$2:$E$9,MATCH(E12,Products!$A$2:$A$9,0)) -> 2412 | M12: =K12-L12 -> 1776 | N12: Online | O12: Marc Dubois
A13: SO-25012 | B13: 45663 | C13: Central Europe | D13: Austria | E13: P-400 | F13: =INDEX(Products!$B$2:$B$9,MATCH(E13,Products!$A$2:$A$9,0)) -> Mounting Kit | G13: =INDEX(Products!$C$2:$C$9,MATCH(E13,Products!$A$2:$A$9,0)) -> Accessories | H13: 8 | I13: =INDEX(Products!$D$2:$D$9,MATCH(E13,Products!$A$2:$A$9,0)) -> 39 | J13: 0 | K13: =H13*I13*(1-J13) -> 312 | L13: =H13*INDEX(Products!$E$2:$E$9,MATCH(E13,Products!$A$2:$A$9,0)) -> 252 | M13: =K13-L13 -> 60 | N13: Direct | O13: Anna Nowak
... A1331: SO-26330 | B1331: 46203 | C1331: Asia Pacific | D1331: Australia | E1331: P-210 | F1331: =INDEX(Products!$B$2:$B$9,MATCH(E1331,Products!$A$2:$A$9,0)) -> Analytics Plus | G1331: =INDEX(Products!$C$2:$C$9,MATCH(E1331,Products!$A$2:$A$9,0)) -> Software | H1331: 1 | I1331: =INDEX(Products!$D$2:$D$9,MATCH(E1331,Products!$A$2:$A$9,0)) -> 290 | J1331: 0 | K1331: =H1331*I1331*(1-J1331) -> 290 | L1331: =H1331*INDEX(Products!$E$2:$E$9,MATCH(E1331,Products!$A$2:$A$9,0)) -> 41 | M1331: =K1331-L1331 -> 249 | N1331: Direct | O1331: Kenji Sato

Sheet Products
A1: Product ID | B1: Product | C1: Category | D1: List Price (EUR) | E1: Unit Cost (EUR) | F1: List Margin %
A2: P-100 | B2: Sensor Hub S | C2: Hardware | D2: 189 | E2: 98 | F2: =IFERROR((D2-E2)/D2,0) -> 0.48148148
A3: P-110 | B3: Sensor Hub Pro | C3: Hardware | D3: 349 | E3: 201 | F3: =IFERROR((D3-E3)/D3,0) -> 0.42406877
A4: P-120 | B4: Edge Gateway | C4: Hardware | D4: 899 | E4: 612 | F4: =IFERROR((D4-E4)/D4,0) -> 0.3192436
A5: P-200 | B5: Analytics Basic | C5: Software | D5: 120 | E5: 18 | F5: =IFERROR((D5-E5)/D5,0) -> 0.85
A6: P-210 | B6: Analytics Plus | C6: Software | D6: 290 | E6: 41 | F6: =IFERROR((D6-E6)/D6,0) -> 0.85862069
A7: P-300 | B7: Install Service | C7: Services | D7: 450 | E7: 310 | F7: =IFERROR((D7-E7)/D7,0) -> 0.31111111
A8: P-310 | B8: Premium Support | C8: Services | D8: 600 | E8: 395 | F8: =IFERROR((D8-E8)/D8,0) -> 0.34166667
A9: P-400 | B9: Mounting Kit | C9: Accessories | D9: 39 | E9: 31.5 | F9: =IFERROR((D9-E9)/D9,0) -> 0.19230769

Sheet Targets
A1: Region | B1: Quarter | C1: Start | D1: End | E1: Target (EUR) | F1: Actual Revenue (EUR) | G1: Attainment % | H1: Gap (EUR)
A2: Western Europe | B2: 2025-Q1 | C2: 45658 | D2: 45747 | E2: 89000 | F2: =SUMIFS(Orders!$K$2:$K$1331,Orders!$C$2:$C$1331,A2,Orders!$B$2:$B$1331,">="&C2,Orders!$B$2:$B$1331,"<="&D2) -> 78351.1 | G2: =IFERROR(F2/E2,0) -> 0.88034944 | H2: =F2-E2 -> -10648.9
A3: Western Europe | B3: 2025-Q2 | C3: 45748 | D3: 45838 | E3: 83000 | F3: =SUMIFS(Orders!$K$2:$K$1331,Orders!$C$2:$C$1331,A3,Orders!$B$2:$B$1331,">="&C3,Orders!$B$2:$B$1331,"<="&D3) -> 77750.35 | G3: =IFERROR(F3/E3,0) -> 0.9367512 | H3: =F3-E3 -> -5249.65
A4: Western Europe | B4: 2025-Q3 | C4: 45839 | D4: 45930 | E4: 80000 | F4: =SUMIFS(Orders!$K$2:$K$1331,Orders!$C$2:$C$1331,A4,Orders!$B$2:$B$1331,">="&C4,Orders!$B$2:$B$1331,"<="&D4) -> 75015 | G4: =IFERROR(F4/E4,0) -> 0.9376875 | H4: =F4-E4 -> -4985
A5: Western Europe | B5: 2025-Q4 | C5: 45931 | D5: 46022 | E5: 119000 | F5: =SUMIFS(Orders!$K$2:$K$1331,Orders!$C$2:$C$1331,A5,Orders!$B$2:$B$1331,">="&C5,Orders!$B$2:$B$1331,"<="&D5) -> 107740.5 | G5: =IFERROR(F5/E5,0) -> 0.90538235 | H5: =F5-E5 -> -11259.5
A6: Western Europe | B6: 2026-Q1 | C6: 46023 | D6: 46112 | E6: 69000 | F6: =SUMIFS(Orders!$K$2:$K$1331,Orders!$C$2:$C$1331,A6,Orders!$B$2:$B$1331,">="&C6,Orders!$B$2:$B$1331,"<="&D6) -> 62391.1 | G6: =IFERROR(F6/E6,0) -> 0.90421884 | H6: =F6-E6 -> -6608.9
A7: Western Europe | B7: 2026-Q2 | C7: 46113 | D7: 46203 | E7: 73000 | F7: =SUMIFS(Orders!$K$2:$K$1331,Orders!$C$2:$C$1331,A7,Orders!$B$2:$B$1331,">="&C7,Orders!$B$2:$B$1331,"<="&D7) -> 61513.45 | G7: =IFERROR(F7/E7,0) -> 0.84265 | H7: =F7-E7 -> -11486.55
A8: Central Europe | B8: 2025-Q1 | C8: 45658 | D8: 45747 | E8: 71000 | F8: =SUMIFS(Orders!$K$2:$K$1331,Orders!$C$2:$C$1331,A8,Orders!$B$2:$B$1331,">="&C8,Orders!$B$2:$B$1331,"<="&D8) -> 71407.5 | G8: =IFERROR(F8/E8,0) -> 1.0057394 | H8: =F8-E8 -> 407.5
A9: Central Europe | B9: 2025-Q2 | C9: 45748 | D9: 45838 | E9: 95500 | F9: =SUMIFS(Orders!$K$2:$K$1331,Orders!$C$2:$C$1331,A9,Orders!$B$2:$B$1331,">="&C9,Orders!$B$2:$B$1331,"<="&D9) -> 92630.65 | G9: =IFERROR(F9/E9,0) -> 0.96995445 | H9: =F9-E9 -> -2869.35
A10: Central Europe | B10: 2025-Q3 | C10: 45839 | D10: 45930 | E10: 54500 | F10: =SUMIFS(Orders!$K$2:$K$1331,Orders!$C$2:$C$1331,A10,Orders!$B$2:$B$1331,">="&C10,Orders!$B$2:$B$1331,"<="&D10) -> 56503 | G10: =IFERROR(F10/E10,0) -> 1.0367523 | H10: =F10-E10 -> 2003
A11: Central Europe | B11: 2025-Q4 | C11: 45931 | D11: 46022 | E11: 119000 | F11: =SUMIFS(Orders!$K$2:$K$1331,Orders!$C$2:$C$1331,A11,Orders!$B$2:$B$1331,">="&C11,Orders!$B$2:$B$1331,"<="&D11) -> 117748.9 | G11: =IFERROR(F11/E11,0) -> 0.98948655 | H11: =F11-E11 -> -1251.1
A12: Central Europe | B12: 2026-Q1 | C12: 46023 | D12: 46112 | E12: 48000 | F12: =SUMIFS(Orders!$K$2:$K$1331,Orders!$C$2:$C$1331,A12,Orders!$B$2:$B$1331,">="&C12,Orders!$B$2:$B$1331,"<="&D12) -> 49567.75 | G12: =IFERROR(F12/E12,0) -> 1.0326615 | H12: =F12-E12 -> 1567.75
A13: Central Europe | B13: 2026-Q2 | C13: 46113 | D13: 46203 | E13: 70500 | F13: =SUMIFS(Orders!$K$2:$K$1331,Orders!$C$2:$C$1331,A13,Orders!$B$2:$B$1331,">="&C13,Orders!$B$2:$B$1331,"<="&D13) -> 73286.9 | G13: =IFERROR(F13/E13,0) -> 1.0395305 | H13: =F13-E13 -> 2786.9
... A31: Latin America | B31: 2026-Q2 | C31: 46113 | D31: 46203 | E31: 27000 | F31: =SUMIFS(Orders!$K$2:$K$1331,Orders!$C$2:$C$1331,A31,Orders!$B$2:$B$1331,">="&C31,Orders!$B$2:$B$1331,"<="&D31) -> 26787.85 | G31: =IFERROR(F31/E31,0) -> 0.99214259 | H31: =F31-E31 -> -212.15

Sheet README
A1: Sample sales data for the agent sandbox Excel demo (fictional)
A3: Orders: one row per order, Jan 2025 - Jun 2026. Revenue = Units x Unit Price x (1 - Discount %).
A4: Products: catalog with list prices and unit costs. Orders look up name, category, price and cost here.
A5: Targets: quarterly revenue targets per region, with actuals summed from Orders.
A6: Color code: blue = input values, green = values pulled from another sheet, black = formulas.
A7: All names, prices, costs, orders and targets are fictional sample data.
A9: Questions to try with excel_agent.py:
A10: Which region had the highest revenue, and by how much?
A11: Which regions missed their quarterly targets most often?
A12: Which product has the lowest gross margin, and why?
A13: How does revenue change by month? Is there seasonality?
A14: Do partner orders earn less margin than direct ones?
A15: Which sales rep generated the most gross margin in 2025?
